Metadata-Version: 1.0
Name: distGB-probability
Version: 0.2
Summary: Gaussian and Binomial distributions
Home-page: UNKNOWN
Author: Aritra Ghosh
Author-email: aritra.dravid007@gmail.com
License: UNKNOWN
Platform: UNKNOWN
